zebr0/__init__.py
zebr0-0.17.0.data/scripts/zebr0-setup
zebr0-0.17.0.dist-info/LICENSE
zebr0-0.17.0.dist-info/METADATA
zebr0-0.17.0.dist-info/WHEEL
zebr0-0.17.0.dist-info/top_level.txt
zebr0-0.17.0.dist-info/RECORD
